zee/__init__.py
zee/dicts.py
zee/modules.py
zee-0.0.4.dist-info/LICENSE
zee-0.0.4.dist-info/METADATA
zee-0.0.4.dist-info/WHEEL
zee-0.0.4.dist-info/top_level.txt
zee-0.0.4.dist-info/RECORD
